LICENSE
README.md
setup.py
ironsms/__init__.py
ironsms/api/__init__.py
ironsms/api/asyncio.py
ironsms/api/sync.py
ironsms/exceptions/__init__.py
ironsms/exceptions/activation.py
ironsms/exceptions/bad_key.py
ironsms/exceptions/bad_query.py
ironsms/exceptions/base.py
ironsms/exceptions/limits.py
ironsms/exceptions/numbers.py
ironsms/exceptions/service.py
ironsms/types/__init__.py
ironsms/types/balance.py
ironsms/types/country.py
ironsms/types/phone.py
ironsms/types/service.py
ironsmslib.egg-info/PKG-INFO
ironsmslib.egg-info/SOURCES.txt
ironsmslib.egg-info/dependency_links.txt
ironsmslib.egg-info/requires.txt
ironsmslib.egg-info/top_level.txt