Metadata-Version: 2.1
Name: ironsmslib
Version: 0.1.2
Summary: Library for API iron-sms.com
Home-page: https://github.com/viuipan/ironsmslib
Author: viuipan
Author-email: viuipan@gmail.com
License: MIT
Platform: UNKNOWN
License-File: LICENSE
